{
    "S Spandau Bhf (Berlin)": "Spandau",
    "S Grünau (Berlin)": "Grünau",
    "S Birkenwerder Bhf": "Birkenwerder",
    "S Südkreuz Bhf (Berlin)": "Südkreuz",
    "S Königs Wusterhausen Bhf": "S Königs Wusterhausen",
    "S Westend (Berlin)": "Westend",
    "S Wildau": "Wildau",
    "S Ostbahnhof (Berlin)": "Ostbahnhof",
    "S Blankenburg (Berlin)": "Blankenburg",
    "S Schöneweide": "Schöneweide",
    "S Adlershof": "Adlershof",
    "S Köpenick": "Köpenick",
    "S+U Gesundbrunnen Bhf (Berlin)": "Gesundbrunnen",
    "S+U Pankow (Berlin)": "Pankow",
    "S+U Tempelhof (Berlin)": "Tempelhof",
    "S+U Alexanderplatz (Berlin)": "Alexanderplatz",
    "S+U Friedrichstr. Bhf (Berlin)": "Friedrichsstraße",
    "Flughafen BER - Terminal 1-2": "BER T. 1-2",
    "Flughafen BER Terminal 5": "BER T. 5",
    "Rahnsdorf/Waldschänke": "Rahnsdorf",
    "Landschaftspark Johannisthal": "Johannisthal",
    "Ersatzverkehr S Adlershof": "Adlershof",
    "Ersatzverkehr -> Falkenberg": "Falkenberg",
    "Mahlsdorf, Rahnsdorfer Str.": "Mahlsdorf",
    "Krankenhaus Köpenick": "Köpenick",
    "Schloßplatz Köpenick": "Köpenick"
}
